simulor/__init__.py
simulor/engine.py
simulor/py.typed
simulor/allocation/__init__.py
simulor/allocation/models.py
simulor/alpha/__init__.py
simulor/alpha/models.py
simulor/alpha/signal.py
simulor/analytics/__init__.py
simulor/analytics/metrics.py
simulor/analytics/performance.py
simulor/analytics/result.py
simulor/analytics/returns.py
simulor/analytics/tearsheet.py
simulor/analytics/visualization.py
simulor/base/__init__.py
simulor/base/collections.py
simulor/core/__init__.py
simulor/core/connectors.py
simulor/core/events.py
simulor/core/protocols.py
simulor/data/__init__.py
simulor/data/cache.py
simulor/data/csv_feed.py
simulor/data/market_store.py
simulor/data/providers/__init__.py
simulor/data/providers/base.py
simulor/data/providers/columns.py
simulor/data/providers/csv.py
simulor/data/providers/symbol_parser.py
simulor/execution/__init__.py
simulor/execution/models.py
simulor/execution/settlement.py
simulor/execution/live/__init__.py
simulor/execution/live/longport.py
simulor/execution/simulation/__init__.py
simulor/execution/simulation/broker.py
simulor/execution/simulation/cost_models.py
simulor/execution/simulation/fill_models.py
simulor/execution/simulation/latency_model.py
simulor/logging/__init__.py
simulor/portfolio/__init__.py
simulor/portfolio/fund.py
simulor/portfolio/manager.py
simulor/portfolio/models.py
simulor/portfolio/position.py
simulor/portfolio/recorder.py
simulor/risk/__init__.py
simulor/risk/models.py
simulor/strategy/__init__.py
simulor/strategy/strategy.py
simulor/types/__init__.py
simulor/types/common.py
simulor/types/instruments.py
simulor/types/market_data.py
simulor/types/orders.py
simulor/universe/__init__.py
simulor/universe/models.py
simulor-0.1.0b1.dist-info/licenses/LICENSE
simulor-0.1.0b1.dist-info/METADATA
simulor-0.1.0b1.dist-info/WHEEL
simulor-0.1.0b1.dist-info/top_level.txt
simulor-0.1.0b1.dist-info/RECORD
