Metadata-Version: 2.4
Name: simulor
Version: 0.1.0b1
Summary: Production-ready event-driven backtesting framework with institutional-grade analytics
Author: Simulor Contributors
License: MIT
Project-URL: Bug Tracker, https://github.com/alasdairpan/simulor/issues
Project-URL: Documentation, https://simulor.readthedocs.io
Project-URL: Homepage, https://github.com/alasdairpan/simulor
Project-URL: Repository, https://github.com/alasdairpan/simulor
Keywords: backtesting,trading,quantitative,finance,algorithmic-trading
Classifier: Development Status :: 3 - Alpha
Classifier: Intended Audience :: Developers
Classifier: Intended Audience :: Financial and Insurance Industry
Classifier: License :: OSI Approved :: MIT License
Classifier: Programming Language :: Python :: 3
Classifier: Programming Language :: Python :: 3.12
Classifier: Programming Language :: Rust
Classifier: Topic :: Office/Business :: Financial :: Investment
Classifier: Topic :: Scientific/Engineering
Requires-Python: >=3.12
License-File: LICENSE
Requires-Dist: numpy>=1.24.0
Requires-Dist: pandas>=2.0.0
Requires-Dist: pyarrow>=12.0.0
Requires-Dist: polars>=0.19.0
Requires-Dist: plotly>=5.14.0
Requires-Dist: pydantic>=2.0.0
Requires-Dist: python-dateutil>=2.8.0
Provides-Extra: dev
Requires-Dist: pytest>=7.4.0; extra == "dev"
Requires-Dist: pytest-cov>=4.1.0; extra == "dev"
Requires-Dist: pytest-xdist>=3.3.0; extra == "dev"
Requires-Dist: hypothesis>=6.82.0; extra == "dev"
Requires-Dist: ruff>=0.1.0; extra == "dev"
Requires-Dist: mypy>=1.5.0; extra == "dev"
Requires-Dist: black>=23.7.0; extra == "dev"
Requires-Dist: pre-commit>=3.3.0; extra == "dev"
Provides-Extra: docs
Requires-Dist: sphinx>=7.0.0; extra == "docs"
Requires-Dist: sphinx-rtd-theme>=1.3.0; extra == "docs"
Requires-Dist: myst-parser>=2.0.0; extra == "docs"
Provides-Extra: jupyter
Requires-Dist: jupyter>=1.0.0; extra == "jupyter"
Requires-Dist: ipywidgets>=8.0.0; extra == "jupyter"
Requires-Dist: matplotlib>=3.7.0; extra == "jupyter"
Provides-Extra: longport
Requires-Dist: longport>=3.0.20; extra == "longport"
Dynamic: license-file
